{"section":"OTHERS","key":"non_serializable","title":"non-serializable type throws (Int8Array)","description":"A root `Int8Array` is non-serializable, so the factory renders as alwaysThrow and every encoder / decoder invocation throws for both JSON and binary.","notes":["No value-first builder exists for Int8Array, so all schema variants are not-supported and test data is empty."],"pureType":"createJsonEncoder<Int8Array>(undefined, {strategy: 'clone'})","schema":"","generated":"import {__rt_NzL_dfPvHfh} from 'virtual:rt/NzL_dfPvHfh.js';\nexport const __rt_BPD_dfPvHfh=['jeCL',()=>[__rt_NzL_dfPvHfh],,'BPD_dfPvHfh','Int8Array','const pjsFn = utl.getRT(\\'NzL_dfPvHfh\\').fn;function BPD_dfPvHfh(v){return JSON.stringify(pjsFn(v));}return BPD_dfPvHfh'];\n\n\nexport const __rt_NzL_dfPvHfh=['pjs',,,'NzL_dfPvHfh','Int8Array',undefined,false,undefined,undefined,undefined,'PJS002','__bench__/OTHERS__non_serializable__clone.ts:3:60'];"}